dtool_lookup_server_notification_plugin/__init__.py
dtool_lookup_server_notification_plugin/config.py
dtool_lookup_server_notification_plugin/elasticsearch.py
dtool_lookup_server_notification_plugin/version.py
dtool_lookup_server_notification_plugin/webhook.py
dtool_lookup_server_notification_plugin-0.2.2.dist-info/LICENSE
dtool_lookup_server_notification_plugin-0.2.2.dist-info/METADATA
dtool_lookup_server_notification_plugin-0.2.2.dist-info/WHEEL
dtool_lookup_server_notification_plugin-0.2.2.dist-info/entry_points.txt
dtool_lookup_server_notification_plugin-0.2.2.dist-info/top_level.txt
dtool_lookup_server_notification_plugin-0.2.2.dist-info/RECORD
