Metadata-Version: 2.1
Name: dtool-lookup-server-notification-plugin
Version: 0.2.2
Summary: dtool lookup server plugin for receiving elastic-search update notifications
Home-page: https://github.com/IMTEK-Simulation/dtool-lookup-server-notification-plugin
Download-URL: https://github.com/IMTEK-Simulation/dtool-lookup-server-notification-plugin/tarball/0.2.2
Author: Lars Pastewka
Author-email: lars.pastewka@imtek.uni-freiburg.de
License: MIT
Platform: UNKNOWN
License-File: LICENSE
Requires-Dist: dtool-lookup-server (>=0.17.2)
Requires-Dist: dtoolcore (>=3.17.0)
Requires-Dist: dtool-s3 (>=0.13.0)
